hcpyutils/__init__.py
hcpyutils/dataformat.py
hcpyutils-0.1.0.dist-info/METADATA
hcpyutils-0.1.0.dist-info/WHEEL
hcpyutils-0.1.0.dist-info/top_level.txt
hcpyutils-0.1.0.dist-info/zip-safe
hcpyutils-0.1.0.dist-info/RECORD
