Metadata-Version: 2.1
Name: hcpyutils
Version: 0.1.0
Summary: python工具包
Home-page: https://github.com/yin
Author: yinjian
Author-email: 599243079@qq.com
License: MIT
Platform: UNKNOWN
Classifier: Intended Audience :: Developers
Classifier: Programming Language :: Python
Classifier: Programming Language :: Python :: 3
Classifier: Programming Language :: Python :: 3.4
Classifier: Programming Language :: Python :: 3.5
Classifier: Programming Language :: Python :: 3.6
Classifier: Topic :: Software Development :: Libraries
Requires-Dist: requests (>=2.19.1)
Requires-Dist: lxml (>=3.7.1)
